{
  "objectInfo" : {
    "id" : "5xtA2R7e8yqeLFyjHd84EJ",
    "name" : "PullByCommitHash_Mapping - Move",
    "type" : "DTEMPLATE",
    "metadata" : {
      "modelVersion" : {
        "major" : 0,
        "minor" : 0
      },
      "repoInfo" : {
        "repoHandle" : "010002170000000002LA"
      },
      "contextAttributes" : [ {
        "name" : "id",
        "value" : "@1"
      } ],
      "additionalInfo" : {
        "description" : "",
        "contentType" : "JSON",
        "documentState" : "INVALID"
      }
    }
  },
  "dataFileExtension" : "zip",
  "updateTime" : "2023-08-21T01:51:33.567Z",
  "objectRefs" : [ ]
}